pangeapy/__init__.py
pangeapy/cell.py
pangeapy/meta.py
pangeapy/models.py
pangeapy-0.0.dist-info/LICENSE
pangeapy-0.0.dist-info/METADATA
pangeapy-0.0.dist-info/WHEEL
pangeapy-0.0.dist-info/top_level.txt
pangeapy-0.0.dist-info/RECORD
